pyB12SPS/__init__.py
pyB12SPS/pyB12SPS.py
pyB12SPS/pyB12SPSGUI.py
pyB12SPS/pyB12SPSGUI.ui
pyB12SPS-0.1.5.dist-info/LICENSE.txt
pyB12SPS-0.1.5.dist-info/METADATA
pyB12SPS-0.1.5.dist-info/WHEEL
pyB12SPS-0.1.5.dist-info/entry_points.txt
pyB12SPS-0.1.5.dist-info/top_level.txt
pyB12SPS-0.1.5.dist-info/RECORD
